is_wire/__init__.py
is_wire/core/__init__.py
is_wire/core/channel.py
is_wire/core/logger.py
is_wire/core/message.py
is_wire/core/subscription.py
is_wire/core/utils.py
is_wire/core/tracing/__init__.py
is_wire/core/tracing/propagation.py
is_wire/core/tracing/tracer.py
is_wire/core/wire/__init__.py
is_wire/core/wire/content_type.py
is_wire/core/wire/conversion.py
is_wire/core/wire/status.py
is_wire/core/wire/wire_pb2.py
is_wire/rpc/__init__.py
is_wire/rpc/context.py
is_wire/rpc/interceptor.py
is_wire/rpc/log_interceptor.py
is_wire/rpc/metrics_interceptor.py
is_wire/rpc/service_provider.py
is_wire/rpc/tracing_interceptor.py
is_wire_mod-0.0.5.dist-info/METADATA
is_wire_mod-0.0.5.dist-info/WHEEL
is_wire_mod-0.0.5.dist-info/top_level.txt
is_wire_mod-0.0.5.dist-info/RECORD
