Metadata-Version: 2.1
Name: is-wire-mod
Version: 0.0.5
Summary: UNKNOWN
Home-page: http://github.com/wagnercotta/is-wire-py-mod
Author: wagnercotta
Author-email: UNKNOWN
License: MIT
Platform: UNKNOWN
Requires-Dist: colorlog (==3.1.4)
Requires-Dist: amqp (==2.4.2)
Requires-Dist: enum34 (==1.1.6)
Requires-Dist: protobuf (==3.6.0)
Requires-Dist: opencensus (==0.5.0)
Requires-Dist: prometheus-client (==0.3.1)
